kanye.py
kanye-0.1.0.dist-info/LICENSE
kanye-0.1.0.dist-info/WHEEL
kanye-0.1.0.dist-info/METADATA
kanye-0.1.0.dist-info/RECORD
